limesrail/__init__.py
limesrail/client.py
limesrail-0.1.0.dist-info/METADATA
limesrail-0.1.0.dist-info/WHEEL
limesrail-0.1.0.dist-info/top_level.txt
limesrail-0.1.0.dist-info/RECORD
