Metadata-Version: 2.4
Name: limesrail
Version: 0.1.0
Summary: The official Python SDK for Limesrail Observability
Home-page: https://github.com/Limesrail/limesrail
Author: Limesrail Team
Author-email: support@limesrail.com
Classifier: Programming Language :: Python :: 3
Classifier: License :: OSI Approved :: MIT License
Classifier: Operating System :: OS Independent
Requires-Python: >=3.7
Requires-Dist: requests>=2.25.0
Requires-Dist: aiohttp>=3.8.0
Requires-Dist: typing-extensions>=4.0.0; python_version < "3.10"
Dynamic: author
Dynamic: author-email
Dynamic: classifier
Dynamic: description
Dynamic: description-content-type
Dynamic: home-page
Dynamic: requires-dist
Dynamic: requires-python
Dynamic: summary
